protoai/__init__.py
protoai/app.py
protoai/message.py
protoai/typing.py
protoai/config/__init__.py
protoai/config/base.py
protoai/config/logger.py
protoai-0.1.2.dist-info/LICENSE
protoai-0.1.2.dist-info/METADATA
protoai-0.1.2.dist-info/WHEEL
protoai-0.1.2.dist-info/top_level.txt
protoai-0.1.2.dist-info/RECORD
