Metadata-Version: 2.2
Name: protoai
Version: 0.1.2
Summary: A Basic Python library that helps you Integrate OpenAI to your ProtoPie projects.
Author: Nestor
Author-email: admin@nestor.me
License-File: LICENSE
Requires-Dist: annotated-types==0.7.0; python_version >= "3.8"
Requires-Dist: anyio==4.8.0; python_version >= "3.9"
Requires-Dist: certifi==2025.1.31; python_version >= "3.6"
Requires-Dist: charset-normalizer==3.4.1; python_version >= "3.7"
Requires-Dist: distro==1.9.0; python_version >= "3.6"
Requires-Dist: h11==0.14.0; python_version >= "3.7"
Requires-Dist: httpcore==1.0.7; python_version >= "3.8"
Requires-Dist: httpx==0.28.1; python_version >= "3.8"
Requires-Dist: idna==3.10; python_version >= "3.6"
Requires-Dist: jiter==0.9.0; python_version >= "3.8"
Requires-Dist: openai==1.66.2; python_version >= "3.8"
Requires-Dist: pydantic==2.10.6; python_version >= "3.8"
Requires-Dist: pydantic-core==2.27.2; python_version >= "3.8"
Requires-Dist: pyyaml==6.0.2; python_version >= "3.8"
Requires-Dist: requests==2.32.3; python_version >= "3.8"
Requires-Dist: sniffio==1.3.1; python_version >= "3.7"
Requires-Dist: tqdm==4.67.1; python_version >= "3.7"
Requires-Dist: typing-extensions==4.12.2; python_version >= "3.8"
Requires-Dist: urllib3==2.3.0; python_version >= "3.9"
Dynamic: author
Dynamic: author-email
Dynamic: description
Dynamic: description-content-type
Dynamic: requires-dist
Dynamic: summary
